{"stats": {"errors": 0, "failures": 0, "passes": 8, "skipped": 0, "encoding": "UTF-8", "total": 8}, "results": [{"classname": "index_test:TestRegression", "name": "test_attendance", "time": 0.00018477439880371094, "type": "success"}, {"classname": "index_test:TestRegression", "name": "test_attendance_with_friends", "time": 8.058547973632812e-05, "type": "success"}, {"classname": "index_test:TestRegression", "name": "test_build_starting_line", "time": 8.845329284667969e-05, "type": "success"}, {"classname": "index_test:TestRegression", "name": "test_expected_value_for_line", "time": 6.67572021484375e-05, "type": "success"}, {"classname": "index_test:TestRegression", "name": "test_m_b_data", "time": 9.179115295410156e-05, "type": "success"}, {"classname": "index_test:TestRegression", "name": "test_m_b_trace", "time": 7.2479248046875e-05, "type": "success"}, {"classname": "index_test:TestRegression", "name": "test_marginal_return_on_budget", "time": 7.05718994140625e-05, "type": "success"}, {"classname": "index_test:TestRegression", "name": "test_y_intercept", "time": 7.033348083496094e-05, "type": "success"}]}